aac/__init__.py
aac/__main__.py
aac/aac.aac
aac/context/__init__.py
aac/context/constants.py
aac/context/definition.py
aac/context/definition_parser.py
aac/context/language_context.py
aac/context/language_error.py
aac/context/lexeme.py
aac/context/source_location.py
aac/context/util.py
aac/execute/__init__.py
aac/execute/aac_execution_result.py
aac/execute/command_line.py
aac/execute/hookspecs.py
aac/execute/plugin_manager.py
aac/execute/plugin_runner.py
aac/in_out/__init__.py
aac/in_out/constants.py
aac/in_out/paths.py
aac/in_out/files/__init__.py
aac/in_out/files/aac_file.py
aac/in_out/files/find.py
aac/in_out/parser/__init__.py
aac/in_out/parser/_cache.py
aac/in_out/parser/_cache_manager.py
aac/in_out/parser/_parse_source.py
aac/in_out/parser/_parser_error.py
aac/in_out/parser/_yaml.py
aac/plugins/__init__.py
aac/plugins/aac_primitives/__init__.py
aac/plugins/aac_primitives/aac_primitive_constraints.aac
aac/plugins/aac_primitives/aac_primitive_constraints_impl.py
aac/plugins/check/__init__.py
aac/plugins/check/check_aac.aac
aac/plugins/check/check_aac_impl.py
aac/plugins/constraint_assignment_arguments/__init__.py
aac/plugins/constraint_assignment_arguments/constraint_assignment_arguments.aac
aac/plugins/constraint_assignment_arguments/constraint_assignment_arguments_impl.py
aac/plugins/exclusive_fields/__init__.py
aac/plugins/exclusive_fields/exclusive_fields.aac
aac/plugins/exclusive_fields/exclusive_fields_impl.py
aac/plugins/gen_plugin/__init__.py
aac/plugins/gen_plugin/gen_plugin.aac
aac/plugins/gen_plugin/gen_plugin_generator.aac
aac/plugins/gen_plugin/gen_plugin_impl.py
aac/plugins/gen_plugin/templates/command_example_page.jinja2
aac/plugins/gen_plugin/templates/empty.jinja2
aac/plugins/gen_plugin/templates/feature_file.jinja2
aac/plugins/gen_plugin/templates/manifest_in.jinja2
aac/plugins/gen_plugin/templates/plugin_documentation.jinja2
aac/plugins/gen_plugin/templates/plugin_impl.jinja2
aac/plugins/gen_plugin/templates/plugin_init.jinja2
aac-0.5.21.dist-info/METADATA
aac-0.5.21.dist-info/WHEEL
aac-0.5.21.dist-info/entry_points.txt
aac-0.5.21.dist-info/top_level.txt
aac-0.5.21.dist-info/RECORD
