Metadata-Version: 2.4
Name: aac
Version: 0.5.21
Summary: A distinctly different take on Model-Based System Engineering (MBSE) that allows a system modeller to define a system in simple yaml. 
Author-email: AaC Dev Team <asdfasdaf@email.com>
License: MIT License
Project-URL: Homepage, https://github.com/DevOps-MBSE/AaC
Project-URL: Issues, https://github.com/DevOps-MBSE/AaC/issues
Keywords: SysML,Architecture-as-Code,System Engineering,MBSE
Classifier: Programming Language :: Python :: 3
Classifier: License :: OSI Approved :: MIT License
Classifier: Operating System :: OS Independent
Classifier: Topic :: Scientific/Engineering
Requires-Python: >=3.9.13
Requires-Dist: attrs~=22.2.0
Requires-Dist: pyrsistent~=0.19.3
Requires-Dist: PyYAML~=6.0.0
Requires-Dist: types-PyYAML~=6.0.12.2
Requires-Dist: six~=1.16.0
Requires-Dist: click~=8.1.3
Requires-Dist: pathspec~=0.10.3
Requires-Dist: regex~=2022.10.31
Requires-Dist: typing-extensions~=4.9.0
Requires-Dist: pluggy~=1.0.0
Requires-Dist: Jinja2~=3.1.2
Requires-Dist: black>=23.9.1
Requires-Dist: MarkupSafe~=2.1.1
Requires-Dist: pygls~=0.13.1
Requires-Dist: fastapi~=0.109.1
Requires-Dist: starlette>=0.22.0
Requires-Dist: anyio<5,~=3.6.2
Requires-Dist: sniffio~=1.3.0
Requires-Dist: uvicorn~=0.20.0
Requires-Dist: requests>=2.28.1
Requires-Dist: wheel~=0.42.0
Requires-Dist: pip-tools>=6.9.0
Requires-Dist: tomli>=2.0.1; python_version < "3.11"
Requires-Dist: platformdirs>=2.4
Requires-Dist: coverage>=6.0
Requires-Dist: mccabe>=0.6.1
Requires-Dist: mypy~=1.1.0
Requires-Dist: mypy-extensions~=1.0.0
Requires-Dist: pycodestyle>=2.8.0
Requires-Dist: pyflakes>=2.4
Requires-Dist: build>=1.0.0
Requires-Dist: twine==3.4.2
Requires-Dist: pipdeptree>=2.2.0
Requires-Dist: Pygments>=2.5.1
Requires-Dist: types-PyYAML>=6.0.9
Requires-Dist: requests>=2.27.0
Provides-Extra: doc
Requires-Dist: sphinx>=7.3.7; extra == "doc"
Requires-Dist: sphinxcontrib-applehelp~=1.0.2; extra == "doc"
Requires-Dist: sphinxcontrib-devhelp~=1.0.2; extra == "doc"
Requires-Dist: sphinxcontrib-htmlhelp~=2.0.0; extra == "doc"
Requires-Dist: sphinxcontrib-jsmath~=1.0.1; extra == "doc"
Requires-Dist: sphinxcontrib-qthelp~=1.0.3; extra == "doc"
Requires-Dist: sphinxcontrib-serializinghtml~=1.1.9; extra == "doc"
Requires-Dist: sphinx-copybutton~=0.5.2; extra == "doc"
Requires-Dist: sphinx_contributors~=0.2.7; extra == "doc"
Requires-Dist: sphinx-autobuild~=2021.3.14; extra == "doc"
Requires-Dist: sphinx-simplepdf~=1.6.0; extra == "doc"
Requires-Dist: furo~=2024.5.6; extra == "doc"
Requires-Dist: docutils~=0.19; extra == "doc"
Requires-Dist: myst-parser~=2.0.0; extra == "doc"
Requires-Dist: pytz~=2023.3; extra == "doc"
Provides-Extra: test
Requires-Dist: build>=1.0.0; extra == "test"
Requires-Dist: tox>=3.24; extra == "test"
Requires-Dist: parameterized>=0.9.0; extra == "test"
Requires-Dist: behave>=1.2.6; extra == "test"
Requires-Dist: coverage>=6.0; extra == "test"
Requires-Dist: flake8>=4.0; extra == "test"
Requires-Dist: flake8-docstrings>=1.6.0; extra == "test"
Requires-Dist: flake8-fixme>=1.1.1; extra == "test"
Requires-Dist: flake8-eradicate>=1.5.0; extra == "test"
Requires-Dist: flake8-assertive>=1.3.0; extra == "test"
Requires-Dist: eradicate<3.0,>=2.0; extra == "test"
Requires-Dist: httpx>=0.23.0; extra == "test"
Provides-Extra: all
Requires-Dist: aac[doc]; extra == "all"
Requires-Dist: aac[test]; extra == "all"
